aprs_assistant/__about__.py
aprs_assistant/__init__.py
aprs_assistant/__main__.py
aprs_assistant/_bandcond.py
aprs_assistant/_bing.py
aprs_assistant/_bot.py
aprs_assistant/_cache.py
aprs_assistant/_callsign.py
aprs_assistant/_constants.py
aprs_assistant/_gpt.py
aprs_assistant/_itu_prefixes.py
aprs_assistant/_location.py
aprs_assistant/_tool_definitions.py
aprs_assistant/_weather.py
aprs_assistant-0.0.4.dist-info/METADATA
aprs_assistant-0.0.4.dist-info/WHEEL
aprs_assistant-0.0.4.dist-info/licenses/LICENSE.txt
aprs_assistant-0.0.4.dist-info/RECORD
