Metadata-Version: 2.3
Name: aprs-assistant
Version: 0.0.4
Summary: An LLM-based assistant for the Automatic Packet Reporting System (APRS).
Project-URL: Documentation, https://github.com/afourney/aprs-assistant#readme
Project-URL: Homepage, https://github.com/afourney/aprs-assistant
Project-URL: Source, https://github.com/afourney/aprs-assistant
Project-URL: Issues, https://github.com/afourney/aprs-assistant/issues
Author-email: Adam Fourney <adam.fourney@gmail.com>
License-Expression: MIT
License-File: LICENSE.txt
Classifier: Development Status :: 4 - Beta
Classifier: Programming Language :: Python
Classifier: Programming Language :: Python :: 3.8
Classifier: Programming Language :: Python :: 3.9
Classifier: Programming Language :: Python :: 3.10
Classifier: Programming Language :: Python :: 3.11
Classifier: Programming Language :: Python :: 3.12
Classifier: Programming Language :: Python :: Implementation :: CPython
Classifier: Programming Language :: Python :: Implementation :: PyPy
Requires-Python: >=3.8
Requires-Dist: maidenhead
Requires-Dist: openai
Requires-Dist: pytz
Requires-Dist: requests
Requires-Dist: timezonefinder
Requires-Dist: xmltodict
